nuaal/__init__.py
nuaal/definitions.py
nuaal/Models/ApicEmModels.py
nuaal/Models/BaseModels.py
nuaal/Models/CiscoApiModels.py
nuaal/Models/Cisco_IOS_Model.py
nuaal/Models/__init__.py
nuaal/Parsers/CiscoIOSParser.py
nuaal/Parsers/CiscoNXOSParser.py
nuaal/Parsers/JuniperJUNOSParser.py
nuaal/Parsers/Parser.py
nuaal/Parsers/PatternsLib.py
nuaal/Parsers/RegexBuilder.py
nuaal/Parsers/__init__.py
nuaal/Readers/Reader.py
nuaal/Readers/__init__.py
nuaal/Writers/ExcelWriter.py
nuaal/Writers/Writer.py
nuaal/Writers/__init__.py
nuaal/connections/__init__.py
nuaal/connections/api/RestBase.py
nuaal/connections/api/RestBase2.py
nuaal/connections/api/__init__.py
nuaal/connections/api/apic_em/ApicEmBase.py
nuaal/connections/api/apic_em/ApicEmPnpClient.py
nuaal/connections/api/apic_em/__init__.py
nuaal/connections/api/ciscoapi/CiscoApiBase.py
nuaal/connections/api/ciscoapi/CiscoEoxApi.py
nuaal/connections/api/ciscoapi/CiscoPsirtApi.py
nuaal/connections/api/ciscoapi/EoXApi.py
nuaal/connections/api/ciscoapi/__init__.py
nuaal/connections/api/dnac/DnacBase.py
nuaal/connections/api/dnac/__init__.py
nuaal/connections/api/epnm/EpnmBase.py
nuaal/connections/api/epnm/__init__.py
nuaal/connections/api/nxos/NxOsBase.py
nuaal/connections/api/nxos/__init__.py
nuaal/connections/cli/Cisco_IOS_Cli.py
nuaal/connections/cli/CliBase.py
nuaal/connections/cli/CliMultiRunner.py
nuaal/connections/cli/GetCliHandler.py
nuaal/connections/cli/__init__.py
nuaal/connections/snmp/SNMP_Base.py
nuaal/connections/snmp/__init__.py
nuaal/data/patterns/cisco_ios/dir_all-filesystems.json
nuaal/data/patterns/cisco_ios/show_authentication_sessions.json
nuaal/data/patterns/cisco_ios/show_authentication_sessions_interface.json
nuaal/data/patterns/cisco_ios/show_boot.json
nuaal/data/patterns/cisco_ios/show_bootvar.json
nuaal/data/patterns/cisco_ios/show_cdp_neighbors_detail.json
nuaal/data/patterns/cisco_ios/show_device-tracking_database_detail.json
nuaal/data/patterns/cisco_ios/show_etherchannel_summary.json
nuaal-0.1.23.dist-info/LICENSE
nuaal-0.1.23.dist-info/METADATA
nuaal-0.1.23.dist-info/WHEEL
nuaal-0.1.23.dist-info/top_level.txt
nuaal-0.1.23.dist-info/RECORD
