Metadata-Version: 2.1
Name: nuaal
Version: 0.1.23
Summary: Network Unified Abstraction API Library
Home-page: https://github.com/mijujda/nuaal
Author: Miroslav Hudec
Author-email: mijujda@gmail.com
License: UNKNOWN
Platform: UNKNOWN
License-File: LICENSE
Requires-Dist: netmiko
Requires-Dist: requests
Requires-Dist: xlsxwriter
